{"lastScanAt":"2026-06-22T17:42:31.100Z","signals":[{"id":"DELHIVERY","symbol":"DELHIVERY","company_name":"Delhivery Limited","market_cap":362292707328,"market_cap_cr":36229,"current_price":483.8,"price_change_pct":4.92,"resistance_price":487.5,"distance_pct":0.76,"current_volume":12505943,"avg_volume_1m":2623301,"avg_volume_2m":2792891,"avg_volume_3m":2888636,"volume_ratio":4.77,"breakout_score":100,"signal_type":"STRONG_BUY"},{"id":"BAJAJHLDNG","symbol":"BAJAJHLDNG","company_name":"Bajaj Holdings & Investment Limited","market_cap":1212542877696,"market_cap_cr":121254,"current_price":10895,"price_change_pct":2.04,"resistance_price":10931,"distance_pct":0.33,"current_volume":97371,"avg_volume_1m":46008,"avg_volume_2m":44744,"avg_volume_3m":48905,"volume_ratio":2.12,"breakout_score":95,"signal_type":"STRONG_BUY"},{"id":"CIPLA","symbol":"CIPLA","company_name":"Cipla Limited","market_cap":1143666507776,"market_cap_cr":114367,"current_price":1415.7,"price_change_pct":4.73,"resistance_price":1432,"distance_pct":1.14,"current_volume":3368537,"avg_volume_1m":1618419,"avg_volume_2m":1814306,"avg_volume_3m":1872104,"volume_ratio":2.08,"breakout_score":95,"signal_type":"STRONG_BUY"},{"id":"DBL","symbol":"DBL","company_name":"Dilip Buildcon Limited","market_cap":73896148992,"market_cap_cr":7390,"current_price":454.9,"price_change_pct":3.5,"resistance_price":463.3,"distance_pct":1.81,"current_volume":225633,"avg_volume_1m":106518,"avg_volume_2m":124493,"avg_volume_3m":157523,"volume_ratio":2.12,"breakout_score":95,"signal_type":"STRONG_BUY"},{"id":"IEX","symbol":"IEX","company_name":"Indian Energy Exchange Limited","market_cap":111767257088,"market_cap_cr":11177,"current_price":125.68,"price_change_pct":2.36,"resistance_price":126.19,"distance_pct":0.4,"current_volume":11351196,"avg_volume_1m":4682193,"avg_volume_2m":5561001,"avg_volume_3m":6502801,"volume_ratio":2.42,"breakout_score":95,"signal_type":"STRONG_BUY"},{"id":"LOTUSDEV","symbol":"LOTUSDEV","company_name":"Sri Lotus Developers and Realty Limited","market_cap":71651786752,"market_cap_cr":7165,"current_price":146.61,"price_change_pct":2.9,"resistance_price":149.5,"distance_pct":1.93,"current_volume":1145440,"avg_volume_1m":461159,"avg_volume_2m":550110,"avg_volume_3m":927926,"volume_ratio":2.48,"breakout_score":95,"signal_type":"STRONG_BUY"},{"id":"MAHLIFE","symbol":"MAHLIFE","company_name":"Mahindra Lifespace Developers Limited","market_cap":76814041088,"market_cap_cr":7681,"current_price":360.05,"price_change_pct":2.19,"resistance_price":362,"distance_pct":0.54,"current_volume":294830,"avg_volume_1m":129693,"avg_volume_2m":182620,"avg_volume_3m":222221,"volume_ratio":2.27,"breakout_score":95,"signal_type":"STRONG_BUY"},{"id":"BASF","symbol":"BASF","company_name":"BASF India Limited","market_cap":154655260672,"market_cap_cr":15466,"current_price":3572.9,"price_change_pct":1.98,"resistance_price":3611,"distance_pct":1.06,"current_volume":69130,"avg_volume_1m":17401,"avg_volume_2m":28304,"avg_volume_3m":28164,"volume_ratio":3.97,"breakout_score":90,"signal_type":"STRONG_BUY"},{"id":"ITCHOTELS","symbol":"ITCHOTELS","company_name":"ITC Hotels Limited","market_cap":367811952640,"market_cap_cr":36781,"current_price":176.58,"price_change_pct":3.31,"resistance_price":185.5,"distance_pct":4.81,"current_volume":13095648,"avg_volume_1m":4101330,"avg_volume_2m":3590281,"avg_volume_3m":5148794,"volume_ratio":3.19,"breakout_score":90,"signal_type":"STRONG_BUY"},{"id":"KIRLFER","symbol":"KIRLFER","company_name":"Kirloskar Ferrous Industries Limited","market_cap":82174451712,"market_cap_cr":8217,"current_price":498.05,"price_change_pct":4.46,"resistance_price":500,"distance_pct":0.39,"current_volume":1207374,"avg_volume_1m":438677,"avg_volume_2m":269037,"avg_volume_3m":231214,"volume_ratio":2.75,"breakout_score":90,"signal_type":"STRONG_BUY"},{"id":"LEMONTREE","symbol":"LEMONTREE","company_name":"Lemon Tree Hotels Limited","market_cap":94031904768,"market_cap_cr":9403,"current_price":118.75,"price_change_pct":5.05,"resistance_price":121.98,"distance_pct":2.65,"current_volume":16988707,"avg_volume_1m":3978053,"avg_volume_2m":3206757,"avg_volume_3m":5329196,"volume_ratio":4.27,"breakout_score":90,"signal_type":"STRONG_BUY"},{"id":"SWANCORP","symbol":"SWANCORP","company_name":"SWAN CORP LIMITED","market_cap":102406373376,"market_cap_cr":10241,"current_price":326.7,"price_change_pct":2.66,"resistance_price":339,"distance_pct":3.63,"current_volume":6736145,"avg_volume_1m":970134,"avg_volume_2m":1041343,"avg_volume_3m":1421079,"volume_ratio":6.94,"breakout_score":90,"signal_type":"STRONG_BUY"},{"id":"TIMKEN","symbol":"TIMKEN","company_name":"Timken India Limited","market_cap":282897678336,"market_cap_cr":28290,"current_price":3761,"price_change_pct":1.94,"resistance_price":3775,"distance_pct":0.37,"current_volume":404069,"avg_volume_1m":67362,"avg_volume_2m":75789,"avg_volume_3m":69220,"volume_ratio":6,"breakout_score":90,"signal_type":"STRONG_BUY"},{"id":"BDL","symbol":"BDL","company_name":"Bharat Dynamics Limited","market_cap":515643441152,"market_cap_cr":51564,"current_price":1406.7,"price_change_pct":2.42,"resistance_price":1426,"distance_pct":1.35,"current_volume":2708266,"avg_volume_1m":1627787,"avg_volume_2m":1356695,"avg_volume_3m":1490504,"volume_ratio":1.66,"breakout_score":85,"signal_type":"STRONG_BUY"},{"id":"DEEPAKNTR","symbol":"DEEPAKNTR","company_name":"Deepak Nitrite Limited","market_cap":227980967936,"market_cap_cr":22798,"current_price":1671.5,"price_change_pct":1.65,"resistance_price":1704.9,"distance_pct":1.96,"current_volume":288838,"avg_volume_1m":110694,"avg_volume_2m":172472,"avg_volume_3m":210491,"volume_ratio":2.61,"breakout_score":85,"signal_type":"STRONG_BUY"},{"id":"EIHOTEL","symbol":"EIHOTEL","company_name":"EIH Limited","market_cap":206463975424,"market_cap_cr":20646,"current_price":330.15,"price_change_pct":2.58,"resistance_price":330.65,"distance_pct":0.15,"current_volume":364738,"avg_volume_1m":211026,"avg_volume_2m":165699,"avg_volume_3m":784034,"volume_ratio":1.73,"breakout_score":85,"signal_type":"STRONG_BUY"},{"id":"PARADEEP","symbol":"PARADEEP","company_name":"Paradeep Phosphates Limited","market_cap":144274571264,"market_cap_cr":14427,"current_price":138.97,"price_change_pct":2.02,"resistance_price":138.48,"distance_pct":-0.35,"current_volume":7346413,"avg_volume_1m":3916071,"avg_volume_2m":5603818,"avg_volume_3m":5990715,"volume_ratio":1.88,"breakout_score":85,"signal_type":"STRONG_BUY"},{"id":"PRICOLLTD","symbol":"PRICOLLTD","company_name":"Pricol Limited","market_cap":69947793408,"market_cap_cr":6995,"current_price":573.9,"price_change_pct":2.64,"resistance_price":584,"distance_pct":1.73,"current_volume":786446,"avg_volume_1m":438142,"avg_volume_2m":814245,"avg_volume_3m":629375,"volume_ratio":1.79,"breakout_score":85,"signal_type":"STRONG_BUY"},{"id":"SANSERA","symbol":"SANSERA","company_name":"Sansera Engineering Limited","market_cap":186460078080,"market_cap_cr":18646,"current_price":2991.4,"price_change_pct":1.55,"resistance_price":2992.2,"distance_pct":0.03,"current_volume":616754,"avg_volume_1m":243962,"avg_volume_2m":294629,"avg_volume_3m":282320,"volume_ratio":2.53,"breakout_score":85,"signal_type":"STRONG_BUY"},{"id":"SONACOMS","symbol":"SONACOMS","company_name":"Sona BLW Precision Forgings Limited","market_cap":386283634688,"market_cap_cr":38628,"current_price":621,"price_change_pct":1.17,"resistance_price":621.8,"distance_pct":0.13,"current_volume":3272779,"avg_volume_1m":1495332,"avg_volume_2m":2137686,"avg_volume_3m":2311859,"volume_ratio":2.19,"breakout_score":85,"signal_type":"STRONG_BUY"},{"id":"SUPRAJIT","symbol":"SUPRAJIT","company_name":"Suprajit Engineering Limited","market_cap":65320902656,"market_cap_cr":6532,"current_price":476.2,"price_change_pct":2.07,"resistance_price":481,"distance_pct":1,"current_volume":732968,"avg_volume_1m":412669,"avg_volume_2m":242998,"avg_volume_3m":203933,"volume_ratio":1.78,"breakout_score":85,"signal_type":"STRONG_BUY"},{"id":"TVSHLTD","symbol":"TVSHLTD","company_name":"TVS Holdings Limited","market_cap":276977516544,"market_cap_cr":27698,"current_price":13690,"price_change_pct":4.25,"resistance_price":13690,"distance_pct":0,"current_volume":6795,"avg_volume_1m":3861,"avg_volume_2m":3958,"avg_volume_3m":5294,"volume_ratio":1.76,"breakout_score":85,"signal_type":"STRONG_BUY"},{"id":"AAVAS","symbol":"AAVAS","company_name":"Aavas Financiers Limited","market_cap":116283465728,"market_cap_cr":11628,"current_price":1466.6,"price_change_pct":-0.36,"resistance_price":1468,"distance_pct":0.1,"current_volume":815540,"avg_volume_1m":225061,"avg_volume_2m":152150,"avg_volume_3m":166207,"volume_ratio":3.62,"breakout_score":80,"signal_type":"BREAKOUT_WATCH"},{"id":"BBTC","symbol":"BBTC","company_name":"The Bombay Burmah Trading Corporation Limited","market_cap":110888493056,"market_cap_cr":11089,"current_price":1589.3,"price_change_pct":3.36,"resistance_price":1610.8,"distance_pct":1.33,"current_volume":147679,"avg_volume_1m":39616,"avg_volume_2m":48193,"avg_volume_3m":60028,"volume_ratio":3.73,"breakout_score":80,"signal_type":"BREAKOUT_WATCH"},{"id":"ETHOSLTD","symbol":"ETHOSLTD","company_name":"Ethos Limited","market_cap":65609859072,"market_cap_cr":6561,"current_price":2452,"price_change_pct":2.99,"resistance_price":2477.9,"distance_pct":1.05,"current_volume":51435,"avg_volume_1m":13758,"avg_volume_2m":26821,"avg_volume_3m":32144,"volume_ratio":3.74,"breakout_score":80,"signal_type":"BREAKOUT_WATCH"},{"id":"HNDFDS","symbol":"HNDFDS","company_name":"Hindustan Foods Limited","market_cap":66663723008,"market_cap_cr":6666,"current_price":550.2,"price_change_pct":0.88,"resistance_price":553.45,"distance_pct":0.59,"current_volume":221119,"avg_volume_1m":67187,"avg_volume_2m":64608,"avg_volume_3m":62816,"volume_ratio":3.29,"breakout_score":80,"signal_type":"BREAKOUT_WATCH"},{"id":"ZYDUSWELL","symbol":"ZYDUSWELL","company_name":"Zydus Wellness Limited","market_cap":170707288064,"market_cap_cr":17071,"current_price":536.55,"price_change_pct":4.72,"resistance_price":542,"distance_pct":1.01,"current_volume":1363456,"avg_volume_1m":368966,"avg_volume_2m":438378,"avg_volume_3m":1512312,"volume_ratio":3.7,"breakout_score":80,"signal_type":"BREAKOUT_WATCH"},{"id":"BAJAJHFL","symbol":"BAJAJHFL","company_name":"Bajaj Housing Finance Limited","market_cap":741250891776,"market_cap_cr":74125,"current_price":89,"price_change_pct":0.72,"resistance_price":89.2,"distance_pct":0.22,"current_volume":11527385,"avg_volume_1m":4997411,"avg_volume_2m":4681497,"avg_volume_3m":6450754,"volume_ratio":2.31,"breakout_score":75,"signal_type":"BREAKOUT_WATCH"},{"id":"CEATLTD","symbol":"CEATLTD","company_name":"CEAT Limited","market_cap":141622951936,"market_cap_cr":14162,"current_price":3510.6,"price_change_pct":1.76,"resistance_price":3575,"distance_pct":1.8,"current_volume":183269,"avg_volume_1m":120668,"avg_volume_2m":203909,"avg_volume_3m":165884,"volume_ratio":1.52,"breakout_score":75,"signal_type":"BREAKOUT_WATCH"},{"id":"COCHINSHIP","symbol":"COCHINSHIP","company_name":"Cochin Shipyard Limited","market_cap":388412473344,"market_cap_cr":38841,"current_price":1476.4,"price_change_pct":1.26,"resistance_price":1524.4,"distance_pct":3.15,"current_volume":2933004,"avg_volume_1m":1133873,"avg_volume_2m":1843738,"avg_volume_3m":1931900,"volume_ratio":2.59,"breakout_score":75,"signal_type":"BREAKOUT_WATCH"},{"id":"ESCORTS","symbol":"ESCORTS","company_name":"Escorts Kubota Limited","market_cap":324624809984,"market_cap_cr":32462,"current_price":2950.4,"price_change_pct":4.58,"resistance_price":3042.7,"distance_pct":3.03,"current_volume":302986,"avg_volume_1m":164775,"avg_volume_2m":159113,"avg_volume_3m":160023,"volume_ratio":1.84,"breakout_score":75,"signal_type":"BREAKOUT_WATCH"},{"id":"GRINFRA","symbol":"GRINFRA","company_name":"G R Infraprojects Limited","market_cap":92803022848,"market_cap_cr":9280,"current_price":959.1,"price_change_pct":7.14,"resistance_price":973.1,"distance_pct":1.44,"current_volume":126775,"avg_volume_1m":44933,"avg_volume_2m":99752,"avg_volume_3m":160029,"volume_ratio":2.82,"breakout_score":75,"signal_type":"BREAKOUT_WATCH"},{"id":"KOVAI","symbol":"KOVAI","company_name":"Kovai Medical Center & Hospital Limited","market_cap":63930167296,"market_cap_cr":6393,"current_price":5842.5,"price_change_pct":0,"resistance_price":5946,"distance_pct":1.74,"current_volume":10511,"avg_volume_1m":5101,"avg_volume_2m":4607,"avg_volume_3m":4030,"volume_ratio":2.06,"breakout_score":75,"signal_type":"BREAKOUT_WATCH"},{"id":"LLOYDSME","symbol":"LLOYDSME","company_name":"Lloyds Metals And Energy Limited","market_cap":1004500484096,"market_cap_cr":100450,"current_price":1785.6,"price_change_pct":1.1,"resistance_price":1790,"distance_pct":0.25,"current_volume":826850,"avg_volume_1m":477878,"avg_volume_2m":568138,"avg_volume_3m":650450,"volume_ratio":1.73,"breakout_score":75,"signal_type":"BREAKOUT_WATCH"},{"id":"MANAPPURAM","symbol":"MANAPPURAM","company_name":"Manappuram Finance Limited","market_cap":307303809024,"market_cap_cr":30730,"current_price":327.15,"price_change_pct":2.67,"resistance_price":334,"distance_pct":2.05,"current_volume":4453465,"avg_volume_1m":2599871,"avg_volume_2m":3629849,"avg_volume_3m":3969534,"volume_ratio":1.71,"breakout_score":75,"signal_type":"BREAKOUT_WATCH"},{"id":"MASFIN","symbol":"MASFIN","company_name":"MAS Financial Services Limited","market_cap":57629593600,"market_cap_cr":5763,"current_price":317.6,"price_change_pct":-0.45,"resistance_price":323.45,"distance_pct":1.81,"current_volume":270282,"avg_volume_1m":106703,"avg_volume_2m":145849,"avg_volume_3m":136435,"volume_ratio":2.53,"breakout_score":75,"signal_type":"BREAKOUT_WATCH"},{"id":"POLICYBZR","symbol":"POLICYBZR","company_name":"PB Fintech Limited","market_cap":771055747072,"market_cap_cr":77106,"current_price":1668.8,"price_change_pct":1.96,"resistance_price":1728.6,"distance_pct":3.46,"current_volume":3541468,"avg_volume_1m":1690095,"avg_volume_2m":1730899,"avg_volume_3m":1735953,"volume_ratio":2.1,"breakout_score":75,"signal_type":"BREAKOUT_WATCH"},{"id":"RECLTD","symbol":"RECLTD","company_name":"REC Limited","market_cap":973897859072,"market_cap_cr":97390,"current_price":369.85,"price_change_pct":4.08,"resistance_price":387.45,"distance_pct":4.54,"current_volume":9410747,"avg_volume_1m":5408208,"avg_volume_2m":5708762,"avg_volume_3m":6915552,"volume_ratio":1.74,"breakout_score":75,"signal_type":"BREAKOUT_WATCH"},{"id":"SCI","symbol":"SCI","company_name":"Shipping Corporation Of India Limited","market_cap":150359916544,"market_cap_cr":15036,"current_price":322.8,"price_change_pct":3.41,"resistance_price":322.8,"distance_pct":0,"current_volume":16897940,"avg_volume_1m":6904445,"avg_volume_2m":9762621,"avg_volume_3m":10610930,"volume_ratio":2.45,"breakout_score":75,"signal_type":"BREAKOUT_WATCH"},{"id":"VESUVIUS","symbol":"VESUVIUS","company_name":"Vesuvius India Limited","market_cap":95300239360,"market_cap_cr":9530,"current_price":469.55,"price_change_pct":1,"resistance_price":484.9,"distance_pct":3.17,"current_volume":130787,"avg_volume_1m":57640,"avg_volume_2m":84119,"avg_volume_3m":110795,"volume_ratio":2.27,"breakout_score":75,"signal_type":"BREAKOUT_WATCH"},{"id":"ABCAPITAL","symbol":"ABCAPITAL","company_name":"Aditya Birla Capital Limited","market_cap":1027635412992,"market_cap_cr":102764,"current_price":391.95,"price_change_pct":4.27,"resistance_price":375.95,"distance_pct":-4.26,"current_volume":11010124,"avg_volume_1m":3529856,"avg_volume_2m":4416623,"avg_volume_3m":4514408,"volume_ratio":3.12,"breakout_score":70,"signal_type":"BREAKOUT_WATCH"},{"id":"AEQUS","symbol":"AEQUS","company_name":"Aequs Limited","market_cap":155108753408,"market_cap_cr":15511,"current_price":236.86,"price_change_pct":6.63,"resistance_price":223.85,"distance_pct":-5.81,"current_volume":20814930,"avg_volume_1m":6851473,"avg_volume_2m":5149578,"avg_volume_3m":4537866,"volume_ratio":3.04,"breakout_score":70,"signal_type":"BREAKOUT_WATCH"},{"id":"APLLTD","symbol":"APLLTD","company_name":"Alembic Pharmaceuticals Limited","market_cap":153466650624,"market_cap_cr":15347,"current_price":780.75,"price_change_pct":2.33,"resistance_price":780.75,"distance_pct":0,"current_volume":222279,"avg_volume_1m":159494,"avg_volume_2m":165101,"avg_volume_3m":152620,"volume_ratio":1.39,"breakout_score":70,"signal_type":"BREAKOUT_WATCH"},{"id":"BHARTIHEXA","symbol":"BHARTIHEXA","company_name":"Bharti Hexacom Limited","market_cap":752550019072,"market_cap_cr":75255,"current_price":1505.1,"price_change_pct":0.71,"resistance_price":1543,"distance_pct":2.46,"current_volume":546044,"avg_volume_1m":124286,"avg_volume_2m":155096,"avg_volume_3m":171394,"volume_ratio":4.39,"breakout_score":70,"signal_type":"BREAKOUT_WATCH"},{"id":"CHALET","symbol":"CHALET","company_name":"Chalet Hotels Limited","market_cap":180462108672,"market_cap_cr":18046,"current_price":824.05,"price_change_pct":2.7,"resistance_price":820.05,"distance_pct":-0.49,"current_volume":207279,"avg_volume_1m":184748,"avg_volume_2m":160465,"avg_volume_3m":152665,"volume_ratio":1.12,"breakout_score":70,"signal_type":"BREAKOUT_WATCH"},{"id":"CIEINDIA","symbol":"CIEINDIA","company_name":"CIE Automotive India Limited","market_cap":179684982784,"market_cap_cr":17968,"current_price":473.65,"price_change_pct":2.08,"resistance_price":485,"distance_pct":2.34,"current_volume":469999,"avg_volume_1m":247094,"avg_volume_2m":572736,"avg_volume_3m":508208,"volume_ratio":1.9,"breakout_score":70,"signal_type":"BREAKOUT_WATCH"},{"id":"CLEAN","symbol":"CLEAN","company_name":"Clean Science and Technology Limited","market_cap":87268573184,"market_cap_cr":8727,"current_price":821.1,"price_change_pct":4.98,"resistance_price":842.9,"distance_pct":2.59,"current_volume":5321082,"avg_volume_1m":475522,"avg_volume_2m":416913,"avg_volume_3m":491757,"volume_ratio":11.19,"breakout_score":70,"signal_type":"BREAKOUT_WATCH"},{"id":"CRISIL","symbol":"CRISIL","company_name":"Crisil Limited","market_cap":308937752576,"market_cap_cr":30894,"current_price":4224.5,"price_change_pct":2.24,"resistance_price":4250,"distance_pct":0.6,"current_volume":51820,"avg_volume_1m":43317,"avg_volume_2m":49315,"avg_volume_3m":69061,"volume_ratio":1.2,"breakout_score":70,"signal_type":"BREAKOUT_WATCH"},{"id":"EBGNG","symbol":"EBGNG","company_name":"GNG Electronics Limited","market_cap":62563823616,"market_cap_cr":6256,"current_price":548.75,"price_change_pct":9.32,"resistance_price":484.8,"distance_pct":-13.19,"current_volume":3843921,"avg_volume_1m":759193,"avg_volume_2m":679423,"avg_volume_3m":593020,"volume_ratio":5.06,"breakout_score":70,"signal_type":"BREAKOUT_WATCH"},{"id":"EDELWEISS","symbol":"EDELWEISS","company_name":"Edelweiss Financial Services Limited","market_cap":123314143232,"market_cap_cr":12331,"current_price":130.28,"price_change_pct":4.47,"resistance_price":129.29,"distance_pct":-0.77,"current_volume":15726980,"avg_volume_1m":5021000,"avg_volume_2m":5295701,"avg_volume_3m":4984943,"volume_ratio":3.13,"breakout_score":70,"signal_type":"BREAKOUT_WATCH"},{"id":"ELECTCAST","symbol":"ELECTCAST","company_name":"Electrosteel Castings Limited","market_cap":51408232448,"market_cap_cr":5141,"current_price":83.16,"price_change_pct":2.24,"resistance_price":84.47,"distance_pct":1.55,"current_volume":2988343,"avg_volume_1m":3149353,"avg_volume_2m":3419684,"avg_volume_3m":3678930,"volume_ratio":0.95,"breakout_score":70,"signal_type":"BREAKOUT_WATCH"},{"id":"FEDFINA","symbol":"FEDFINA","company_name":"Fedbank Financial Services Limited","market_cap":57600569344,"market_cap_cr":5760,"current_price":153.64,"price_change_pct":-0.6,"resistance_price":159.15,"distance_pct":3.46,"current_volume":9013503,"avg_volume_1m":1386493,"avg_volume_2m":1361717,"avg_volume_3m":1174599,"volume_ratio":6.5,"breakout_score":70,"signal_type":"BREAKOUT_WATCH"},{"id":"FINPIPE","symbol":"FINPIPE","company_name":"Finolex Industries Limited","market_cap":110826594304,"market_cap_cr":11083,"current_price":179.24,"price_change_pct":2.08,"resistance_price":179.59,"distance_pct":0.19,"current_volume":1288822,"avg_volume_1m":2640113,"avg_volume_2m":1469002,"avg_volume_3m":1270359,"volume_ratio":0.49,"breakout_score":70,"signal_type":"BREAKOUT_WATCH"},{"id":"GODIGIT","symbol":"GODIGIT","company_name":"Go Digit General Insurance Limited","market_cap":293877121024,"market_cap_cr":29388,"current_price":317.95,"price_change_pct":3.92,"resistance_price":320.9,"distance_pct":0.92,"current_volume":1076570,"avg_volume_1m":1116487,"avg_volume_2m":676619,"avg_volume_3m":564702,"volume_ratio":0.96,"breakout_score":70,"signal_type":"BREAKOUT_WATCH"},{"id":"GPPL","symbol":"GPPL","company_name":"Gujarat Pipavav Port Limited","market_cap":75711627264,"market_cap_cr":7571,"current_price":156.55,"price_change_pct":2.27,"resistance_price":159.23,"distance_pct":1.68,"current_volume":2521003,"avg_volume_1m":2215612,"avg_volume_2m":1570544,"avg_volume_3m":1489016,"volume_ratio":1.14,"breakout_score":70,"signal_type":"BREAKOUT_WATCH"},{"id":"HAPPYFORGE","symbol":"HAPPYFORGE","company_name":"Happy Forgings Limited","market_cap":146740068352,"market_cap_cr":14674,"current_price":1554.8,"price_change_pct":6.13,"resistance_price":1490,"distance_pct":-4.35,"current_volume":672937,"avg_volume_1m":156055,"avg_volume_2m":133552,"avg_volume_3m":112565,"volume_ratio":4.31,"breakout_score":70,"signal_type":"BREAKOUT_WATCH"},{"id":"IDBI","symbol":"IDBI","company_name":"IDBI Bank Limited","market_cap":942448115712,"market_cap_cr":94245,"current_price":87.65,"price_change_pct":5.63,"resistance_price":117.55,"distance_pct":25.44,"current_volume":83807988,"avg_volume_1m":25421074,"avg_volume_2m":17429094,"avg_volume_3m":17643487,"volume_ratio":3.3,"breakout_score":70,"signal_type":"BREAKOUT_WATCH"},{"id":"KIRLOSENG","symbol":"KIRLOSENG","company_name":"Kirloskar Oil Engines Limited","market_cap":347428978688,"market_cap_cr":34743,"current_price":2389.8,"price_change_pct":20,"resistance_price":1990.8,"distance_pct":-20.04,"current_volume":1794364,"avg_volume_1m":447086,"avg_volume_2m":431012,"avg_volume_3m":428940,"volume_ratio":4.01,"breakout_score":70,"signal_type":"BREAKOUT_WATCH"},{"id":"KMEW","symbol":"KMEW","company_name":"Knowledge Marine & Engineering Works Limited","market_cap":57125879808,"market_cap_cr":5713,"current_price":2337,"price_change_pct":12.74,"resistance_price":2285.4,"distance_pct":-2.26,"current_volume":467662,"avg_volume_1m":130402,"avg_volume_2m":172944,"avg_volume_3m":140646,"volume_ratio":3.59,"breakout_score":70,"signal_type":"BREAKOUT_WATCH"},{"id":"NACLIND","symbol":"NACLIND","company_name":"NACL Industries Limited","market_cap":50556739584,"market_cap_cr":5056,"current_price":215.83,"price_change_pct":11.37,"resistance_price":189.86,"distance_pct":-13.68,"current_volume":11606470,"avg_volume_1m":1390403,"avg_volume_2m":966019,"avg_volume_3m":855441,"volume_ratio":8.35,"breakout_score":70,"signal_type":"BREAKOUT_WATCH"},{"id":"NCC","symbol":"NCC","company_name":"NCC Limited","market_cap":100172922880,"market_cap_cr":10017,"current_price":159.55,"price_change_pct":2.38,"resistance_price":171.77,"distance_pct":7.11,"current_volume":6812931,"avg_volume_1m":2138928,"avg_volume_2m":2431694,"avg_volume_3m":2765245,"volume_ratio":3.19,"breakout_score":70,"signal_type":"BREAKOUT_WATCH"},{"id":"NHPC","symbol":"NHPC","company_name":"NHPC Limited","market_cap":785722638336,"market_cap_cr":78572,"current_price":78.22,"price_change_pct":3.17,"resistance_price":78.44,"distance_pct":0.28,"current_volume":50724906,"avg_volume_1m":45467263,"avg_volume_2m":29777821,"avg_volume_3m":25450169,"volume_ratio":1.12,"breakout_score":70,"signal_type":"BREAKOUT_WATCH"},{"id":"NIACL","symbol":"NIACL","company_name":"The New India Assurance Company Limited","market_cap":349557293056,"market_cap_cr":34956,"current_price":212.11,"price_change_pct":4.84,"resistance_price":180.4,"distance_pct":-17.58,"current_volume":80906207,"avg_volume_1m":14358044,"avg_volume_2m":7672225,"avg_volume_3m":7618754,"volume_ratio":5.63,"breakout_score":70,"signal_type":"BREAKOUT_WATCH"},{"id":"PARKHOSPS","symbol":"PARKHOSPS","company_name":"Park Medi World Limited","market_cap":124936003584,"market_cap_cr":12494,"current_price":289.25,"price_change_pct":4.2,"resistance_price":293.8,"distance_pct":1.55,"current_volume":1080813,"avg_volume_1m":887700,"avg_volume_2m":870726,"avg_volume_3m":887392,"volume_ratio":1.22,"breakout_score":70,"signal_type":"BREAKOUT_WATCH"},{"id":"RBA","symbol":"RBA","company_name":"Restaurant Brands Asia Limited","market_cap":56688156672,"market_cap_cr":5669,"current_price":79.68,"price_change_pct":8.16,"resistance_price":69.5,"distance_pct":-14.65,"current_volume":68722103,"avg_volume_1m":9560002,"avg_volume_2m":6441873,"avg_volume_3m":4788574,"volume_ratio":7.19,"breakout_score":70,"signal_type":"BREAKOUT_WATCH"},{"id":"SCHNEIDER","symbol":"SCHNEIDER","company_name":"Schneider Electric Infrastructure Limited","market_cap":333669662720,"market_cap_cr":33367,"current_price":1395.5,"price_change_pct":4.81,"resistance_price":1417.8,"distance_pct":1.57,"current_volume":779275,"avg_volume_1m":634650,"avg_volume_2m":415108,"avg_volume_3m":330633,"volume_ratio":1.23,"breakout_score":70,"signal_type":"BREAKOUT_WATCH"},{"id":"SPLPETRO","symbol":"SPLPETRO","company_name":"Supreme Petrochem Limited","market_cap":145703829504,"market_cap_cr":14570,"current_price":774.85,"price_change_pct":3.28,"resistance_price":805,"distance_pct":3.75,"current_volume":422510,"avg_volume_1m":95065,"avg_volume_2m":94038,"avg_volume_3m":168151,"volume_ratio":4.44,"breakout_score":70,"signal_type":"BREAKOUT_WATCH"},{"id":"SUBROS","symbol":"SUBROS","company_name":"Subros Limited","market_cap":55841804288,"market_cap_cr":5584,"current_price":856,"price_change_pct":14.52,"resistance_price":819,"distance_pct":-4.52,"current_volume":8776852,"avg_volume_1m":453588,"avg_volume_2m":251227,"avg_volume_3m":194651,"volume_ratio":19.35,"breakout_score":70,"signal_type":"BREAKOUT_WATCH"},{"id":"SUMICHEM","symbol":"SUMICHEM","company_name":"Sumitomo Chemical India Limited","market_cap":219075051520,"market_cap_cr":21908,"current_price":438.9,"price_change_pct":-3.05,"resistance_price":453.8,"distance_pct":3.28,"current_volume":1029095,"avg_volume_1m":315358,"avg_volume_2m":356167,"avg_volume_3m":320816,"volume_ratio":3.26,"breakout_score":70,"signal_type":"BREAKOUT_WATCH"},{"id":"TATACOMM","symbol":"TATACOMM","company_name":"Tata Communications Limited","market_cap":587618975744,"market_cap_cr":58762,"current_price":2061.7,"price_change_pct":3.67,"resistance_price":2049.9,"distance_pct":-0.58,"current_volume":2749962,"avg_volume_1m":884503,"avg_volume_2m":807630,"avg_volume_3m":688205,"volume_ratio":3.11,"breakout_score":70,"signal_type":"BREAKOUT_WATCH"},{"id":"TSFINV","symbol":"TSFINV","company_name":"TSF INVESTMENTS LIMITED","market_cap":88122245120,"market_cap_cr":8812,"current_price":399.3,"price_change_pct":0.99,"resistance_price":411.85,"distance_pct":3.05,"current_volume":340748,"avg_volume_1m":106813,"avg_volume_2m":86338,"avg_volume_3m":97388,"volume_ratio":3.19,"breakout_score":70,"signal_type":"BREAKOUT_WATCH"},{"id":"URBANCO","symbol":"URBANCO","company_name":"Urban Company Limited","market_cap":200289501184,"market_cap_cr":20029,"current_price":136.98,"price_change_pct":5.25,"resistance_price":156.19,"distance_pct":12.3,"current_volume":21070045,"avg_volume_1m":4787277,"avg_volume_2m":5187051,"avg_volume_3m":6617131,"volume_ratio":4.4,"breakout_score":70,"signal_type":"BREAKOUT_WATCH"},{"id":"ABREL","symbol":"ABREL","company_name":"Aditya Birla Real Estate Limited","market_cap":145277173760,"market_cap_cr":14528,"current_price":1313.8,"price_change_pct":2.68,"resistance_price":1327.9,"distance_pct":1.06,"current_volume":229704,"avg_volume_1m":196936,"avg_volume_2m":244594,"avg_volume_3m":293045,"volume_ratio":1.17,"breakout_score":65,"signal_type":"MONITOR"},{"id":"AETHER","symbol":"AETHER","company_name":"Aether Industries Limited","market_cap":162811789312,"market_cap_cr":16281,"current_price":1226.8,"price_change_pct":5.55,"resistance_price":1250,"distance_pct":1.86,"current_volume":596195,"avg_volume_1m":309656,"avg_volume_2m":337447,"avg_volume_3m":391292,"volume_ratio":1.93,"breakout_score":65,"signal_type":"MONITOR"},{"id":"AJANTPHARM","symbol":"AJANTPHARM","company_name":"Ajanta Pharma Limited","market_cap":398507147264,"market_cap_cr":39851,"current_price":3189.7,"price_change_pct":4.06,"resistance_price":3228,"distance_pct":1.19,"current_volume":140186,"avg_volume_1m":123838,"avg_volume_2m":130689,"avg_volume_3m":117132,"volume_ratio":1.13,"breakout_score":65,"signal_type":"MONITOR"},{"id":"AMAGI","symbol":"AMAGI","company_name":"Amagi Media Labs Limited","market_cap":114994962432,"market_cap_cr":11499,"current_price":531.55,"price_change_pct":8.71,"resistance_price":450.8,"distance_pct":-17.91,"current_volume":845126,"avg_volume_1m":418643,"avg_volume_2m":345854,"avg_volume_3m":308861,"volume_ratio":2.02,"breakout_score":65,"signal_type":"MONITOR"},{"id":"BAJAJFINSV","symbol":"BAJAJFINSV","company_name":"Bajaj Finserv Limited","market_cap":2848861454336,"market_cap_cr":284886,"current_price":1782.2,"price_change_pct":0.72,"resistance_price":1817.6,"distance_pct":1.95,"current_volume":1828045,"avg_volume_1m":940607,"avg_volume_2m":1012370,"avg_volume_3m":1219652,"volume_ratio":1.94,"breakout_score":65,"signal_type":"MONITOR"},{"id":"BOSCH-HCIL","symbol":"BOSCH-HCIL","company_name":"BOSCH HOME COMFORT INDIA LIMITED","market_cap":211059130368,"market_cap_cr":21106,"current_price":1381.4,"price_change_pct":-0.1,"resistance_price":1395,"distance_pct":0.97,"current_volume":168579,"avg_volume_1m":108253,"avg_volume_2m":61031,"avg_volume_3m":48973,"volume_ratio":1.56,"breakout_score":65,"signal_type":"MONITOR"},{"id":"CANFINHOME","symbol":"CANFINHOME","company_name":"Can Fin Homes Limited","market_cap":118827163648,"market_cap_cr":11883,"current_price":892.4,"price_change_pct":0.8,"resistance_price":910,"distance_pct":1.93,"current_volume":352804,"avg_volume_1m":197510,"avg_volume_2m":181653,"avg_volume_3m":178490,"volume_ratio":1.79,"breakout_score":65,"signal_type":"MONITOR"},{"id":"CASTROLIND","symbol":"CASTROLIND","company_name":"Castrol India Limited","market_cap":184263606272,"market_cap_cr":18426,"current_price":186.29,"price_change_pct":0.26,"resistance_price":188.2,"distance_pct":1.01,"current_volume":2116091,"avg_volume_1m":1075882,"avg_volume_2m":1129829,"avg_volume_3m":1430317,"volume_ratio":1.97,"breakout_score":65,"signal_type":"MONITOR"},{"id":"CCL","symbol":"CCL","company_name":"CCL Products (India) Limited","market_cap":153152765952,"market_cap_cr":15315,"current_price":1148.7,"price_change_pct":1,"resistance_price":1183.1,"distance_pct":2.91,"current_volume":1249899,"avg_volume_1m":700797,"avg_volume_2m":492781,"avg_volume_3m":441192,"volume_ratio":1.78,"breakout_score":65,"signal_type":"MONITOR"},{"id":"ENDURANCE","symbol":"ENDURANCE","company_name":"Endurance Technologies Limited","market_cap":377384337408,"market_cap_cr":37738,"current_price":2682.9,"price_change_pct":2.31,"resistance_price":2693,"distance_pct":0.38,"current_volume":211930,"avg_volume_1m":113598,"avg_volume_2m":144387,"avg_volume_3m":126998,"volume_ratio":1.87,"breakout_score":65,"signal_type":"MONITOR"},{"id":"GRSE","symbol":"GRSE","company_name":"Garden Reach Shipbuilders & Engineers Limited","market_cap":327687471104,"market_cap_cr":32769,"current_price":2860.6,"price_change_pct":2.23,"resistance_price":3130,"distance_pct":8.61,"current_volume":2756536,"avg_volume_1m":941251,"avg_volume_2m":1813940,"avg_volume_3m":1945876,"volume_ratio":2.93,"breakout_score":65,"signal_type":"MONITOR"},{"id":"HSCL","symbol":"HSCL","company_name":"Himadri Speciality Chemical Limited","market_cap":330499981312,"market_cap_cr":33050,"current_price":655.05,"price_change_pct":-2.38,"resistance_price":654.45,"distance_pct":-0.09,"current_volume":24305707,"avg_volume_1m":13394140,"avg_volume_2m":14152186,"avg_volume_3m":10596184,"volume_ratio":1.81,"breakout_score":65,"signal_type":"MONITOR"},{"id":"ICICIPRULI","symbol":"ICICIPRULI","company_name":"ICICI Prudential Life Insurance Company Limited","market_cap":734009622528,"market_cap_cr":73401,"current_price":506.3,"price_change_pct":1.2,"resistance_price":529.3,"distance_pct":4.35,"current_volume":3301402,"avg_volume_1m":1836900,"avg_volume_2m":1705213,"avg_volume_3m":1764870,"volume_ratio":1.8,"breakout_score":65,"signal_type":"MONITOR"},{"id":"INDIAMART","symbol":"INDIAMART","company_name":"Indiamart Intermesh Limited","market_cap":123308294144,"market_cap_cr":12331,"current_price":2050.4,"price_change_pct":-1.87,"resistance_price":2122.2,"distance_pct":3.38,"current_volume":241918,"avg_volume_1m":88092,"avg_volume_2m":86737,"avg_volume_3m":110927,"volume_ratio":2.75,"breakout_score":65,"signal_type":"MONITOR"},{"id":"JSWENERGY","symbol":"JSWENERGY","company_name":"JSW Energy Limited","market_cap":1066537844736,"market_cap_cr":106654,"current_price":582.05,"price_change_pct":2.1,"resistance_price":585.65,"distance_pct":0.61,"current_volume":4308790,"avg_volume_1m":3486560,"avg_volume_2m":3732284,"avg_volume_3m":3964613,"volume_ratio":1.24,"breakout_score":65,"signal_type":"MONITOR"},{"id":"JUBLPHARMA","symbol":"JUBLPHARMA","company_name":"Jubilant Pharmova Limited","market_cap":151489413120,"market_cap_cr":15149,"current_price":956.45,"price_change_pct":-1.02,"resistance_price":959.35,"distance_pct":0.3,"current_volume":139477,"avg_volume_1m":92054,"avg_volume_2m":116993,"avg_volume_3m":140190,"volume_ratio":1.52,"breakout_score":65,"signal_type":"MONITOR"},{"id":"KIRLOSBROS","symbol":"KIRLOSBROS","company_name":"Kirloskar Brothers Limited","market_cap":164638539776,"market_cap_cr":16464,"current_price":2073.3,"price_change_pct":7.22,"resistance_price":2000,"distance_pct":-3.67,"current_volume":3531576,"avg_volume_1m":280131,"avg_volume_2m":178341,"avg_volume_3m":158042,"volume_ratio":12.61,"breakout_score":65,"signal_type":"MONITOR"},{"id":"KIRLPNU","symbol":"KIRLPNU","company_name":"Kirloskar Pneumatic Company Limited","market_cap":135860060160,"market_cap_cr":13586,"current_price":2091.5,"price_change_pct":7.26,"resistance_price":2000,"distance_pct":-4.58,"current_volume":1689413,"avg_volume_1m":269903,"avg_volume_2m":290967,"avg_volume_3m":226024,"volume_ratio":6.26,"breakout_score":65,"signal_type":"MONITOR"},{"id":"METROPOLIS","symbol":"METROPOLIS","company_name":"Metropolis Healthcare Limited","market_cap":112062930944,"market_cap_cr":11206,"current_price":540.5,"price_change_pct":-2.22,"resistance_price":565,"distance_pct":4.34,"current_volume":468843,"avg_volume_1m":212086,"avg_volume_2m":520970,"avg_volume_3m":464009,"volume_ratio":2.21,"breakout_score":65,"signal_type":"MONITOR"},{"id":"MRF","symbol":"MRF","company_name":"MRF Limited","market_cap":557964787712,"market_cap_cr":55796,"current_price":131560,"price_change_pct":2.27,"resistance_price":133950,"distance_pct":1.78,"current_volume":11182,"avg_volume_1m":6301,"avg_volume_2m":6732,"avg_volume_3m":7316,"volume_ratio":1.77,"breakout_score":65,"signal_type":"MONITOR"},{"id":"PGIL","symbol":"PGIL","company_name":"Pearl Global Industries Limited","market_cap":86761480192,"market_cap_cr":8676,"current_price":1878.6,"price_change_pct":4.74,"resistance_price":2000,"distance_pct":6.07,"current_volume":291191,"avg_volume_1m":76265,"avg_volume_2m":102391,"avg_volume_3m":82790,"volume_ratio":3.82,"breakout_score":65,"signal_type":"MONITOR"},{"id":"POWERICA","symbol":"POWERICA","company_name":"Powerica Limited","market_cap":78506459136,"market_cap_cr":7851,"current_price":620.35,"price_change_pct":4.99,"resistance_price":586.3,"distance_pct":-5.81,"current_volume":1082067,"avg_volume_1m":476816,"avg_volume_2m":447855,"avg_volume_3m":534470,"volume_ratio":2.27,"breakout_score":65,"signal_type":"MONITOR"},{"id":"PVRINOX","symbol":"PVRINOX","company_name":"PVR INOX Limited","market_cap":96152494080,"market_cap_cr":9615,"current_price":979.15,"price_change_pct":3.19,"resistance_price":985,"distance_pct":0.59,"current_volume":326505,"avg_volume_1m":181236,"avg_volume_2m":293655,"avg_volume_3m":322344,"volume_ratio":1.8,"breakout_score":65,"signal_type":"MONITOR"},{"id":"RELIGARE","symbol":"RELIGARE","company_name":"Religare Enterprises Limited","market_cap":90607788032,"market_cap_cr":9061,"current_price":265.53,"price_change_pct":4.79,"resistance_price":246.3,"distance_pct":-7.81,"current_volume":2858116,"avg_volume_1m":1197932,"avg_volume_2m":1302643,"avg_volume_3m":1546199,"volume_ratio":2.39,"breakout_score":65,"signal_type":"MONITOR"},{"id":"SAGILITY","symbol":"SAGILITY","company_name":"SAGILITY LIMITED","market_cap":187393572864,"market_cap_cr":18739,"current_price":40.03,"price_change_pct":1.37,"resistance_price":41.14,"distance_pct":2.7,"current_volume":22870782,"avg_volume_1m":13760036,"avg_volume_2m":15803794,"avg_volume_3m":19758114,"volume_ratio":1.66,"breakout_score":65,"signal_type":"MONITOR"},{"id":"SCHAEFFLER","symbol":"SCHAEFFLER","company_name":"Schaeffler India Limited","market_cap":675325607936,"market_cap_cr":67533,"current_price":4320.6,"price_change_pct":-0.21,"resistance_price":4445,"distance_pct":2.8,"current_volume":203962,"avg_volume_1m":86346,"avg_volume_2m":87671,"avg_volume_3m":94470,"volume_ratio":2.36,"breakout_score":65,"signal_type":"MONITOR"},{"id":"UTIAMC","symbol":"UTIAMC","company_name":"UTI Asset Management Company Limited","market_cap":120363974656,"market_cap_cr":12036,"current_price":936.5,"price_change_pct":-1.45,"resistance_price":967,"distance_pct":3.15,"current_volume":211746,"avg_volume_1m":80984,"avg_volume_2m":160990,"avg_volume_3m":182331,"volume_ratio":2.61,"breakout_score":65,"signal_type":"MONITOR"},{"id":"VBL","symbol":"VBL","company_name":"Varun Beverages Limited","market_cap":1734948814848,"market_cap_cr":173495,"current_price":512.95,"price_change_pct":-3.13,"resistance_price":534.7,"distance_pct":4.07,"current_volume":11555863,"avg_volume_1m":5720359,"avg_volume_2m":6667197,"avg_volume_3m":6924038,"volume_ratio":2.02,"breakout_score":65,"signal_type":"MONITOR"},{"id":"ACE","symbol":"ACE","company_name":"Action Construction Equipment Limited","market_cap":120412618752,"market_cap_cr":12041,"current_price":1011.7,"price_change_pct":3.69,"resistance_price":1000,"distance_pct":-1.17,"current_volume":968914,"avg_volume_1m":372037,"avg_volume_2m":423370,"avg_volume_3m":408141,"volume_ratio":2.6,"breakout_score":60,"signal_type":"MONITOR"},{"id":"ARE&M","symbol":"ARE&M","company_name":"Amara Raja Energy & Mobility Limited","market_cap":156889333760,"market_cap_cr":15689,"current_price":857.2,"price_change_pct":1.49,"resistance_price":871,"distance_pct":1.58,"current_volume":795894,"avg_volume_1m":1260283,"avg_volume_2m":952915,"avg_volume_3m":1711130,"volume_ratio":0.63,"breakout_score":60,"signal_type":"MONITOR"},{"id":"ASTRAZEN","symbol":"ASTRAZEN","company_name":"AstraZeneca Pharma India Limited","market_cap":214237495296,"market_cap_cr":21424,"current_price":8569.5,"price_change_pct":1.61,"resistance_price":8670.5,"distance_pct":1.16,"current_volume":6855,"avg_volume_1m":11242,"avg_volume_2m":8311,"avg_volume_3m":9873,"volume_ratio":0.61,"breakout_score":60,"signal_type":"MONITOR"},{"id":"BALUFORGE","symbol":"BALUFORGE","company_name":"Balu Forge Industries Limited","market_cap":52689293312,"market_cap_cr":5269,"current_price":458.2,"price_change_pct":2.11,"resistance_price":480,"distance_pct":4.54,"current_volume":543024,"avg_volume_1m":895717,"avg_volume_2m":752591,"avg_volume_3m":669021,"volume_ratio":0.61,"breakout_score":60,"signal_type":"MONITOR"},{"id":"CEIGALL","symbol":"CEIGALL","company_name":"Ceigall India Limited","market_cap":65440055296,"market_cap_cr":6544,"current_price":375.65,"price_change_pct":0.28,"resistance_price":376,"distance_pct":0.09,"current_volume":1005071,"avg_volume_1m":665331,"avg_volume_2m":777252,"avg_volume_3m":624608,"volume_ratio":1.51,"breakout_score":60,"signal_type":"MONITOR"},{"id":"CRAMC","symbol":"CRAMC","company_name":"Canara Robeco Asset Management Company Limited","market_cap":50691907584,"market_cap_cr":5069,"current_price":254.2,"price_change_pct":-0.16,"resistance_price":258,"distance_pct":1.47,"current_volume":561919,"avg_volume_1m":335558,"avg_volume_2m":400280,"avg_volume_3m":456696,"volume_ratio":1.67,"breakout_score":60,"signal_type":"MONITOR"},{"id":"DRREDDY","symbol":"DRREDDY","company_name":"Dr. Reddy's Laboratories Limited","market_cap":1074778996736,"market_cap_cr":107478,"current_price":1290.7,"price_change_pct":1.46,"resistance_price":1309,"distance_pct":1.4,"current_volume":1618125,"avg_volume_1m":1471763,"avg_volume_2m":2039398,"avg_volume_3m":2342085,"volume_ratio":1.1,"breakout_score":60,"signal_type":"MONITOR"},{"id":"GLAXO","symbol":"GLAXO","company_name":"GlaxoSmithKline Pharmaceuticals Limited","market_cap":400323411968,"market_cap_cr":40032,"current_price":2363.1,"price_change_pct":1.33,"resistance_price":2401.9,"distance_pct":1.62,"current_volume":134012,"avg_volume_1m":146842,"avg_volume_2m":117873,"avg_volume_3m":98169,"volume_ratio":0.91,"breakout_score":60,"signal_type":"MONITOR"},{"id":"IRB","symbol":"IRB","company_name":"IRB Infrastructure Developers Limited","market_cap":262092619776,"market_cap_cr":26209,"current_price":21.7,"price_change_pct":1.21,"resistance_price":21.96,"distance_pct":1.18,"current_volume":13994017,"avg_volume_1m":14191353,"avg_volume_2m":23773080,"avg_volume_3m":23706229,"volume_ratio":0.99,"breakout_score":60,"signal_type":"MONITOR"},{"id":"JKTYRE","symbol":"JKTYRE","company_name":"JK Tyre & Industries Limited","market_cap":118342844416,"market_cap_cr":11834,"current_price":410.5,"price_change_pct":2.29,"resistance_price":419.8,"distance_pct":2.22,"current_volume":1844524,"avg_volume_1m":1922430,"avg_volume_2m":1418331,"avg_volume_3m":1374746,"volume_ratio":0.96,"breakout_score":60,"signal_type":"MONITOR"},{"id":"JSLL","symbol":"JSLL","company_name":"Jeena Sikho Lifecare Limited","market_cap":75680497664,"market_cap_cr":7568,"current_price":608.85,"price_change_pct":9.27,"resistance_price":635,"distance_pct":4.12,"current_volume":5225759,"avg_volume_1m":4478405,"avg_volume_2m":2450327,"avg_volume_3m":1763156,"volume_ratio":1.17,"breakout_score":60,"signal_type":"MONITOR"},{"id":"KSB","symbol":"KSB","company_name":"Ksb Limited","market_cap":164954374144,"market_cap_cr":16495,"current_price":947.8,"price_change_pct":5.01,"resistance_price":1000,"distance_pct":5.22,"current_volume":518097,"avg_volume_1m":202323,"avg_volume_2m":227691,"avg_volume_3m":297616,"volume_ratio":2.56,"breakout_score":60,"signal_type":"MONITOR"},{"id":"METROBRAND","symbol":"METROBRAND","company_name":"Metro Brands Limited","market_cap":284566061056,"market_cap_cr":28457,"current_price":1044.1,"price_change_pct":0.63,"resistance_price":1065,"distance_pct":1.96,"current_volume":91723,"avg_volume_1m":28779,"avg_volume_2m":38305,"avg_volume_3m":39507,"volume_ratio":3.19,"breakout_score":60,"signal_type":"MONITOR"},{"id":"MFSL","symbol":"MFSL","company_name":"Max Financial Services Limited","market_cap":579257040896,"market_cap_cr":57926,"current_price":1686.6,"price_change_pct":1.04,"resistance_price":1718.8,"distance_pct":1.87,"current_volume":640566,"avg_volume_1m":578932,"avg_volume_2m":590416,"avg_volume_3m":726457,"volume_ratio":1.11,"breakout_score":60,"signal_type":"MONITOR"},{"id":"PGEL","symbol":"PGEL","company_name":"PG Electroplast Limited","market_cap":162009677824,"market_cap_cr":16201,"current_price":567.5,"price_change_pct":1.25,"resistance_price":577.95,"distance_pct":1.81,"current_volume":3657699,"avg_volume_1m":3827352,"avg_volume_2m":2998428,"avg_volume_3m":3657701,"volume_ratio":0.96,"breakout_score":60,"signal_type":"MONITOR"},{"id":"POLYMED","symbol":"POLYMED","company_name":"Poly Medicure Limited","market_cap":169612836864,"market_cap_cr":16961,"current_price":1671.4,"price_change_pct":6.91,"resistance_price":1710,"distance_pct":2.26,"current_volume":321531,"avg_volume_1m":239496,"avg_volume_2m":188548,"avg_volume_3m":177992,"volume_ratio":1.34,"breakout_score":60,"signal_type":"MONITOR"},{"id":"POWERMECH","symbol":"POWERMECH","company_name":"Power Mech Projects Limited","market_cap":91538653184,"market_cap_cr":9154,"current_price":2895.3,"price_change_pct":1.95,"resistance_price":2679,"distance_pct":-8.07,"current_volume":744816,"avg_volume_1m":165163,"avg_volume_2m":133167,"avg_volume_3m":134340,"volume_ratio":4.51,"breakout_score":60,"signal_type":"MONITOR"},{"id":"SKFINDIA","symbol":"SKFINDIA","company_name":"SKF India Limited","market_cap":81948368896,"market_cap_cr":8195,"current_price":1657.6,"price_change_pct":1.18,"resistance_price":1693.4,"distance_pct":2.11,"current_volume":36642,"avg_volume_1m":23190,"avg_volume_2m":27060,"avg_volume_3m":33166,"volume_ratio":1.58,"breakout_score":60,"signal_type":"MONITOR"},{"id":"TVSMOTOR","symbol":"TVSMOTOR","company_name":"TVS Motor Company Limited","market_cap":1657921732608,"market_cap_cr":165792,"current_price":3488.7,"price_change_pct":1.33,"resistance_price":3501.7,"distance_pct":0.37,"current_volume":990336,"avg_volume_1m":1075108,"avg_volume_2m":1052752,"avg_volume_3m":1020414,"volume_ratio":0.92,"breakout_score":60,"signal_type":"MONITOR"},{"id":"WABAG","symbol":"WABAG","company_name":"VA Tech Wabag Limited","market_cap":128482435072,"market_cap_cr":12848,"current_price":2061.8,"price_change_pct":3.94,"resistance_price":2000,"distance_pct":-3.09,"current_volume":2102264,"avg_volume_1m":733606,"avg_volume_2m":527698,"avg_volume_3m":498422,"volume_ratio":2.87,"breakout_score":60,"signal_type":"MONITOR"},{"id":"YATHARTH","symbol":"YATHARTH","company_name":"Yatharth Hospital & Trauma Care Services Limited","market_cap":82084282368,"market_cap_cr":8208,"current_price":851.9,"price_change_pct":1.45,"resistance_price":887.85,"distance_pct":4.05,"current_volume":790707,"avg_volume_1m":424433,"avg_volume_2m":458039,"avg_volume_3m":444799,"volume_ratio":1.86,"breakout_score":60,"signal_type":"MONITOR"},{"id":"ACMESOLAR","symbol":"ACMESOLAR","company_name":"Acme Solar Holdings Limited","market_cap":247096066048,"market_cap_cr":24710,"current_price":349.85,"price_change_pct":3.61,"resistance_price":364.8,"distance_pct":4.1,"current_volume":3377952,"avg_volume_1m":3086276,"avg_volume_2m":2255086,"avg_volume_3m":2367965,"volume_ratio":1.09,"breakout_score":55,"signal_type":"MONITOR"},{"id":"AIAENG","symbol":"AIAENG","company_name":"AIA Engineering Limited","market_cap":452417159168,"market_cap_cr":45242,"current_price":4848,"price_change_pct":3.44,"resistance_price":5000,"distance_pct":3.04,"current_volume":245606,"avg_volume_1m":158399,"avg_volume_2m":90928,"avg_volume_3m":84691,"volume_ratio":1.55,"breakout_score":55,"signal_type":"MONITOR"},{"id":"AMBER","symbol":"AMBER","company_name":"Amber Enterprises India Limited","market_cap":278844604416,"market_cap_cr":27884,"current_price":7906.5,"price_change_pct":0.22,"resistance_price":8142.5,"distance_pct":2.9,"current_volume":712294,"avg_volume_1m":431320,"avg_volume_2m":469957,"avg_volume_3m":424936,"volume_ratio":1.65,"breakout_score":55,"signal_type":"MONITOR"},{"id":"BAJAJ-AUTO","symbol":"BAJAJ-AUTO","company_name":"Bajaj Auto Limited","market_cap":2846058348544,"market_cap_cr":284606,"current_price":10191,"price_change_pct":1.24,"resistance_price":10785,"distance_pct":5.51,"current_volume":833885,"avg_volume_1m":376599,"avg_volume_2m":391478,"avg_volume_3m":394656,"volume_ratio":2.21,"breakout_score":55,"signal_type":"MONITOR"},{"id":"BANKBARODA","symbol":"BANKBARODA","company_name":"Bank of Baroda","market_cap":1479268106240,"market_cap_cr":147927,"current_price":286.05,"price_change_pct":1.78,"resistance_price":286.25,"distance_pct":0.07,"current_volume":10869963,"avg_volume_1m":14079360,"avg_volume_2m":12506633,"avg_volume_3m":12344519,"volume_ratio":0.77,"breakout_score":55,"signal_type":"MONITOR"},{"id":"BLUESTARCO","symbol":"BLUESTARCO","company_name":"Blue Star Limited","market_cap":342250061824,"market_cap_cr":34225,"current_price":1664.7,"price_change_pct":-0.22,"resistance_price":1710.6,"distance_pct":2.68,"current_volume":939641,"avg_volume_1m":483157,"avg_volume_2m":531524,"avg_volume_3m":648704,"volume_ratio":1.94,"breakout_score":55,"signal_type":"MONITOR"},{"id":"ENGINERSIN","symbol":"ENGINERSIN","company_name":"Engineers India Limited","market_cap":145287954432,"market_cap_cr":14529,"current_price":258.5,"price_change_pct":3.09,"resistance_price":264.6,"distance_pct":2.31,"current_volume":7498680,"avg_volume_1m":4020261,"avg_volume_2m":4700218,"avg_volume_3m":4949632,"volume_ratio":1.87,"breakout_score":55,"signal_type":"MONITOR"},{"id":"GABRIEL","symbol":"GABRIEL","company_name":"Gabriel India Limited","market_cap":220101967872,"market_cap_cr":22010,"current_price":1241.9,"price_change_pct":3.72,"resistance_price":1154,"distance_pct":-7.62,"current_volume":782586,"avg_volume_1m":485990,"avg_volume_2m":459130,"avg_volume_3m":419708,"volume_ratio":1.61,"breakout_score":55,"signal_type":"MONITOR"},{"id":"GRAVITA","symbol":"GRAVITA","company_name":"Gravita India Limited","market_cap":126736228352,"market_cap_cr":12674,"current_price":1740,"price_change_pct":1.07,"resistance_price":1748.2,"distance_pct":0.47,"current_volume":298776,"avg_volume_1m":182442,"avg_volume_2m":219389,"avg_volume_3m":273352,"volume_ratio":1.64,"breakout_score":55,"signal_type":"MONITOR"},{"id":"INDGN","symbol":"INDGN","company_name":"Indegene Limited","market_cap":130119704576,"market_cap_cr":13012,"current_price":541.45,"price_change_pct":1.7,"resistance_price":554,"distance_pct":2.27,"current_volume":440747,"avg_volume_1m":208806,"avg_volume_2m":241454,"avg_volume_3m":271679,"volume_ratio":2.11,"breakout_score":55,"signal_type":"MONITOR"},{"id":"IREDA","symbol":"IREDA","company_name":"Indian Renewable Energy Development Agency Limited","market_cap":367587950592,"market_cap_cr":36759,"current_price":130.85,"price_change_pct":2.91,"resistance_price":135.5,"distance_pct":3.43,"current_volume":12722599,"avg_volume_1m":7801487,"avg_volume_2m":7203859,"avg_volume_3m":9636868,"volume_ratio":1.63,"breakout_score":55,"signal_type":"MONITOR"},{"id":"KPIL","symbol":"KPIL","company_name":"Kalpataru Projects International Limited","market_cap":245861220352,"market_cap_cr":24586,"current_price":1439.7,"price_change_pct":2.93,"resistance_price":1335,"distance_pct":-7.84,"current_volume":520891,"avg_volume_1m":319024,"avg_volume_2m":252819,"avg_volume_3m":226433,"volume_ratio":1.63,"breakout_score":55,"signal_type":"MONITOR"},{"id":"LAURUSLABS","symbol":"LAURUSLABS","company_name":"Laurus Labs Limited","market_cap":775744389120,"market_cap_cr":77574,"current_price":1435.9,"price_change_pct":1.63,"resistance_price":1457,"distance_pct":1.45,"current_volume":1721622,"avg_volume_1m":1716764,"avg_volume_2m":2049230,"avg_volume_3m":1985464,"volume_ratio":1,"breakout_score":55,"signal_type":"MONITOR"},{"id":"MANKIND","symbol":"MANKIND","company_name":"Mankind Pharma Limited","market_cap":1048307695616,"market_cap_cr":104831,"current_price":2538.3,"price_change_pct":5.14,"resistance_price":2638.6,"distance_pct":3.8,"current_volume":983880,"avg_volume_1m":514945,"avg_volume_2m":652516,"avg_volume_3m":630841,"volume_ratio":1.91,"breakout_score":55,"signal_type":"MONITOR"},{"id":"MANORAMA","symbol":"MANORAMA","company_name":"Manorama Industries Limited","market_cap":92392980480,"market_cap_cr":9239,"current_price":1547.4,"price_change_pct":-0.69,"resistance_price":1585.6,"distance_pct":2.41,"current_volume":256223,"avg_volume_1m":157951,"avg_volume_2m":185091,"avg_volume_3m":163137,"volume_ratio":1.62,"breakout_score":55,"signal_type":"MONITOR"},{"id":"ORKLAINDIA","symbol":"ORKLAINDIA","company_name":"Orkla India Limited","market_cap":83488088064,"market_cap_cr":8349,"current_price":609.45,"price_change_pct":-1.56,"resistance_price":611.25,"distance_pct":0.29,"current_volume":103084,"avg_volume_1m":47467,"avg_volume_2m":56034,"avg_volume_3m":74237,"volume_ratio":2.17,"breakout_score":55,"signal_type":"MONITOR"},{"id":"PFC","symbol":"PFC","company_name":"Power Finance Corporation Limited","market_cap":1455179825152,"market_cap_cr":145518,"current_price":440.95,"price_change_pct":2.31,"resistance_price":467.4,"distance_pct":5.66,"current_volume":10049736,"avg_volume_1m":6106665,"avg_volume_2m":6275449,"avg_volume_3m":7608821,"volume_ratio":1.65,"breakout_score":55,"signal_type":"MONITOR"},{"id":"PRESTIGE","symbol":"PRESTIGE","company_name":"Prestige Estates Projects Limited","market_cap":651479482368,"market_cap_cr":65148,"current_price":1512.5,"price_change_pct":1.02,"resistance_price":1514.7,"distance_pct":0.15,"current_volume":788528,"avg_volume_1m":704116,"avg_volume_2m":633072,"avg_volume_3m":883042,"volume_ratio":1.12,"breakout_score":55,"signal_type":"MONITOR"},{"id":"PWL","symbol":"PWL","company_name":"Physicswallah Limited","market_cap":360778825728,"market_cap_cr":36078,"current_price":126.16,"price_change_pct":2.9,"resistance_price":118.9,"distance_pct":-6.11,"current_volume":27537727,"avg_volume_1m":15991906,"avg_volume_2m":10110406,"avg_volume_3m":8832829,"volume_ratio":1.72,"breakout_score":55,"signal_type":"MONITOR"},{"id":"SEDEMAC","symbol":"SEDEMAC","company_name":"SEDEMAC Mechatronics Limited","market_cap":126195376128,"market_cap_cr":12620,"current_price":2857.2,"price_change_pct":5.98,"resistance_price":2937.1,"distance_pct":2.72,"current_volume":300650,"avg_volume_1m":192664,"avg_volume_2m":228691,"avg_volume_3m":206714,"volume_ratio":1.56,"breakout_score":55,"signal_type":"MONITOR"},{"id":"TORNTPOWER","symbol":"TORNTPOWER","company_name":"Torrent Power Limited","market_cap":743358464000,"market_cap_cr":74336,"current_price":1475.2,"price_change_pct":2.56,"resistance_price":1523.6,"distance_pct":3.18,"current_volume":286457,"avg_volume_1m":426092,"avg_volume_2m":549328,"avg_volume_3m":594107,"volume_ratio":0.67,"breakout_score":55,"signal_type":"MONITOR"},{"id":"TTKPRESTIG","symbol":"TTKPRESTIG","company_name":"TTK Prestige Limited","market_cap":77226655744,"market_cap_cr":7723,"current_price":563.9,"price_change_pct":4.18,"resistance_price":579.5,"distance_pct":2.69,"current_volume":151916,"avg_volume_1m":86054,"avg_volume_2m":481380,"avg_volume_3m":388871,"volume_ratio":1.77,"breakout_score":55,"signal_type":"MONITOR"},{"id":"VIYASH","symbol":"VIYASH","company_name":"Viyash Scientific Limited","market_cap":118368837632,"market_cap_cr":11837,"current_price":271.2,"price_change_pct":6.37,"resistance_price":277.35,"distance_pct":2.22,"current_volume":5316183,"avg_volume_1m":2888478,"avg_volume_2m":2572116,"avg_volume_3m":1978460,"volume_ratio":1.84,"breakout_score":55,"signal_type":"MONITOR"},{"id":"WAAREERTL","symbol":"WAAREERTL","company_name":"Waaree Renewable Technologies Limited","market_cap":104877948928,"market_cap_cr":10488,"current_price":1005.1,"price_change_pct":1.73,"resistance_price":1070.9,"distance_pct":6.14,"current_volume":575224,"avg_volume_1m":194606,"avg_volume_2m":229951,"avg_volume_3m":633925,"volume_ratio":2.96,"breakout_score":55,"signal_type":"MONITOR"},{"id":"WESTLIFE","symbol":"WESTLIFE","company_name":"WESTLIFE FOODWORLD LIMITED","market_cap":75551268864,"market_cap_cr":7555,"current_price":486.75,"price_change_pct":4.21,"resistance_price":496.85,"distance_pct":2.03,"current_volume":108952,"avg_volume_1m":70815,"avg_volume_2m":93608,"avg_volume_3m":137520,"volume_ratio":1.54,"breakout_score":55,"signal_type":"MONITOR"},{"id":"ZFCVINDIA","symbol":"ZFCVINDIA","company_name":"ZF Commercial Vehicle Control Systems India Limited","market_cap":295742570496,"market_cap_cr":29574,"current_price":15592,"price_change_pct":-1.29,"resistance_price":15549,"distance_pct":-0.28,"current_volume":35129,"avg_volume_1m":16662,"avg_volume_2m":16240,"avg_volume_3m":18650,"volume_ratio":2.11,"breakout_score":55,"signal_type":"MONITOR"},{"id":"ACI","symbol":"ACI","company_name":"Archean Chemical Industries Limited","market_cap":65865052160,"market_cap_cr":6587,"current_price":533.5,"price_change_pct":1.09,"resistance_price":548.4,"distance_pct":2.72,"current_volume":174856,"avg_volume_1m":230160,"avg_volume_2m":201934,"avg_volume_3m":189425,"volume_ratio":0.76,"breakout_score":50,"signal_type":"MONITOR"},{"id":"ADANIGREEN","symbol":"ADANIGREEN","company_name":"Adani Green Energy Limited","market_cap":2552958550016,"market_cap_cr":255296,"current_price":1549.9,"price_change_pct":3.16,"resistance_price":1544.8,"distance_pct":-0.33,"current_volume":2955438,"avg_volume_1m":3481290,"avg_volume_2m":4089955,"avg_volume_3m":4566813,"volume_ratio":0.85,"breakout_score":50,"signal_type":"MONITOR"},{"id":"ALKEM","symbol":"ALKEM","company_name":"Alkem Laboratories Limited","market_cap":641705377792,"market_cap_cr":64171,"current_price":5367,"price_change_pct":-0.12,"resistance_price":5464,"distance_pct":1.78,"current_volume":106480,"avg_volume_1m":180081,"avg_volume_2m":134799,"avg_volume_3m":134595,"volume_ratio":0.59,"breakout_score":50,"signal_type":"MONITOR"},{"id":"AMBUJACEM","symbol":"AMBUJACEM","company_name":"Ambuja Cements Limited","market_cap":1063501758464,"market_cap_cr":106350,"current_price":428,"price_change_pct":0.96,"resistance_price":435.9,"distance_pct":1.81,"current_volume":3535861,"avg_volume_1m":3366679,"avg_volume_2m":3544460,"avg_volume_3m":3494319,"volume_ratio":1.05,"breakout_score":50,"signal_type":"MONITOR"},{"id":"ARVINDFASN","symbol":"ARVINDFASN","company_name":"Arvind Fashions Limited","market_cap":64020742144,"market_cap_cr":6402,"current_price":479,"price_change_pct":-1.04,"resistance_price":479.85,"distance_pct":0.18,"current_volume":249711,"avg_volume_1m":189361,"avg_volume_2m":412324,"avg_volume_3m":358908,"volume_ratio":1.32,"breakout_score":50,"signal_type":"MONITOR"},{"id":"ASAHIINDIA","symbol":"ASAHIINDIA","company_name":"Asahi India Glass Limited","market_cap":219810971648,"market_cap_cr":21981,"current_price":862.25,"price_change_pct":1.88,"resistance_price":879.9,"distance_pct":2.01,"current_volume":54496,"avg_volume_1m":120409,"avg_volume_2m":102987,"avg_volume_3m":135811,"volume_ratio":0.45,"breakout_score":50,"signal_type":"MONITOR"},{"id":"AUROPHARMA","symbol":"AUROPHARMA","company_name":"Aurobindo Pharma Limited","market_cap":858406322176,"market_cap_cr":85841,"current_price":1491.9,"price_change_pct":-0.39,"resistance_price":1496.5,"distance_pct":0.31,"current_volume":1718448,"avg_volume_1m":1296825,"avg_volume_2m":1267923,"avg_volume_3m":1431707,"volume_ratio":1.33,"breakout_score":50,"signal_type":"MONITOR"},{"id":"BATAINDIA","symbol":"BATAINDIA","company_name":"Bata India Limited","market_cap":93953630208,"market_cap_cr":9395,"current_price":731,"price_change_pct":-2.23,"resistance_price":735.5,"distance_pct":0.61,"current_volume":544957,"avg_volume_1m":866064,"avg_volume_2m":491130,"avg_volume_3m":409127,"volume_ratio":0.63,"breakout_score":50,"signal_type":"MONITOR"},{"id":"BAYERCROP","symbol":"BAYERCROP","company_name":"Bayer Cropscience Limited","market_cap":187795030016,"market_cap_cr":18780,"current_price":4178.6,"price_change_pct":-2.13,"resistance_price":4639.7,"distance_pct":9.94,"current_volume":149656,"avg_volume_1m":37781,"avg_volume_2m":26460,"avg_volume_3m":26652,"volume_ratio":3.96,"breakout_score":50,"signal_type":"MONITOR"},{"id":"BEML","symbol":"BEML","company_name":"BEML Limited","market_cap":146830180352,"market_cap_cr":14683,"current_price":1762.9,"price_change_pct":0.78,"resistance_price":1783,"distance_pct":1.13,"current_volume":170336,"avg_volume_1m":241466,"avg_volume_2m":268346,"avg_volume_3m":321943,"volume_ratio":0.71,"breakout_score":50,"signal_type":"MONITOR"},{"id":"BRITANNIA","symbol":"BRITANNIA","company_name":"Britannia Industries Limited","market_cap":1256730263552,"market_cap_cr":125673,"current_price":5217.5,"price_change_pct":0.43,"resistance_price":5258,"distance_pct":0.77,"current_volume":261961,"avg_volume_1m":332008,"avg_volume_2m":438997,"avg_volume_3m":434553,"volume_ratio":0.79,"breakout_score":50,"signal_type":"MONITOR"},{"id":"CENTUM","symbol":"CENTUM","company_name":"Centum Electronics Limited","market_cap":54591754240,"market_cap_cr":5459,"current_price":3703.4,"price_change_pct":4.65,"resistance_price":3714,"distance_pct":0.29,"current_volume":71237,"avg_volume_1m":70547,"avg_volume_2m":74084,"avg_volume_3m":81620,"volume_ratio":1.01,"breakout_score":50,"signal_type":"MONITOR"},{"id":"CHOICEIN","symbol":"CHOICEIN","company_name":"Choice International Limited","market_cap":162036482048,"market_cap_cr":16204,"current_price":727.35,"price_change_pct":0.17,"resistance_price":736,"distance_pct":1.18,"current_volume":824151,"avg_volume_1m":677238,"avg_volume_2m":674476,"avg_volume_3m":709231,"volume_ratio":1.22,"breakout_score":50,"signal_type":"MONITOR"},{"id":"CLEANMAX","symbol":"CLEANMAX","company_name":"Clean Max Enviro Energy Solutions Limited","market_cap":174916288512,"market_cap_cr":17492,"current_price":1494,"price_change_pct":9.03,"resistance_price":1421.2,"distance_pct":-5.12,"current_volume":1543021,"avg_volume_1m":436338,"avg_volume_2m":352729,"avg_volume_3m":343608,"volume_ratio":3.54,"breakout_score":50,"signal_type":"MONITOR"},{"id":"CONCORDBIO","symbol":"CONCORDBIO","company_name":"Concord Biotech Limited","market_cap":139934629888,"market_cap_cr":13993,"current_price":1337.6,"price_change_pct":1.71,"resistance_price":1407.9,"distance_pct":4.99,"current_volume":358426,"avg_volume_1m":649524,"avg_volume_2m":437523,"avg_volume_3m":386231,"volume_ratio":0.55,"breakout_score":50,"signal_type":"MONITOR"},{"id":"CRAFTSMAN","symbol":"CRAFTSMAN","company_name":"Craftsman Automation Limited","market_cap":249042501632,"market_cap_cr":24904,"current_price":9522,"price_change_pct":-2.9,"resistance_price":9738,"distance_pct":2.22,"current_volume":305258,"avg_volume_1m":92740,"avg_volume_2m":174256,"avg_volume_3m":126758,"volume_ratio":3.29,"breakout_score":50,"signal_type":"MONITOR"},{"id":"DEVYANI","symbol":"DEVYANI","company_name":"Devyani International Limited","market_cap":144562192384,"market_cap_cr":14456,"current_price":117.25,"price_change_pct":0.29,"resistance_price":118.39,"distance_pct":0.96,"current_volume":2737290,"avg_volume_1m":3211123,"avg_volume_2m":4228719,"avg_volume_3m":4247222,"volume_ratio":0.85,"breakout_score":50,"signal_type":"MONITOR"},{"id":"DODLA","symbol":"DODLA","company_name":"Dodla Dairy Limited","market_cap":68556521472,"market_cap_cr":6856,"current_price":1136.4,"price_change_pct":2.48,"resistance_price":1152.5,"distance_pct":1.4,"current_volume":19200,"avg_volume_1m":16463,"avg_volume_2m":26944,"avg_volume_3m":35945,"volume_ratio":1.17,"breakout_score":50,"signal_type":"MONITOR"},{"id":"E2E","symbol":"E2E","company_name":"E2E Networks Limited","market_cap":91830042624,"market_cap_cr":9183,"current_price":447.1,"price_change_pct":4.98,"resistance_price":453.8,"distance_pct":1.48,"current_volume":3014740,"avg_volume_1m":2311963,"avg_volume_2m":1684259,"avg_volume_3m":1310254,"volume_ratio":1.3,"breakout_score":50,"signal_type":"MONITOR"},{"id":"FINCABLES","symbol":"FINCABLES","company_name":"Finolex Cables Limited","market_cap":182074294272,"market_cap_cr":18207,"current_price":1190.5,"price_change_pct":2.25,"resistance_price":1184.8,"distance_pct":-0.48,"current_volume":813668,"avg_volume_1m":729663,"avg_volume_2m":657178,"avg_volume_3m":606726,"volume_ratio":1.12,"breakout_score":50,"signal_type":"MONITOR"},{"id":"FLUOROCHEM","symbol":"FLUOROCHEM","company_name":"Gujarat Fluorochemicals Limited","market_cap":423076265984,"market_cap_cr":42308,"current_price":3851.4,"price_change_pct":0.3,"resistance_price":3874.9,"distance_pct":0.61,"current_volume":132469,"avg_volume_1m":107901,"avg_volume_2m":118878,"avg_volume_3m":105614,"volume_ratio":1.23,"breakout_score":50,"signal_type":"MONITOR"},{"id":"GALAXYSURF","symbol":"GALAXYSURF","company_name":"Galaxy Surfactants Limited","market_cap":69370765312,"market_cap_cr":6937,"current_price":1956.6,"price_change_pct":0.58,"resistance_price":1960,"distance_pct":0.17,"current_volume":17390,"avg_volume_1m":20302,"avg_volume_2m":16292,"avg_volume_3m":17144,"volume_ratio":0.86,"breakout_score":50,"signal_type":"MONITOR"},{"id":"GESHIP","symbol":"GESHIP","company_name":"The Great Eastern Shipping Company Limited","market_cap":210338873344,"market_cap_cr":21034,"current_price":1473.3,"price_change_pct":2.48,"resistance_price":1502.2,"distance_pct":1.92,"current_volume":452508,"avg_volume_1m":813599,"avg_volume_2m":1598775,"avg_volume_3m":1239651,"volume_ratio":0.56,"breakout_score":50,"signal_type":"MONITOR"},{"id":"GICRE","symbol":"GICRE","company_name":"General Insurance Corporation of India","market_cap":647899906048,"market_cap_cr":64790,"current_price":369.3,"price_change_pct":0.16,"resistance_price":376.4,"distance_pct":1.89,"current_volume":1362176,"avg_volume_1m":2099582,"avg_volume_2m":1231453,"avg_volume_3m":1063713,"volume_ratio":0.65,"breakout_score":50,"signal_type":"MONITOR"},{"id":"GNFC","symbol":"GNFC","company_name":"Gujarat Narmada Valley Fertilizers and Chemicals Limited","market_cap":85446008832,"market_cap_cr":8545,"current_price":581.5,"price_change_pct":2.44,"resistance_price":552,"distance_pct":-5.34,"current_volume":2466238,"avg_volume_1m":551728,"avg_volume_2m":686114,"avg_volume_3m":582616,"volume_ratio":4.47,"breakout_score":50,"signal_type":"MONITOR"},{"id":"GRASIM","symbol":"GRASIM","company_name":"Grasim Industries Limited","market_cap":2153334177792,"market_cap_cr":215333,"current_price":3175.2,"price_change_pct":0.82,"resistance_price":3197.5,"distance_pct":0.7,"current_volume":368610,"avg_volume_1m":649434,"avg_volume_2m":868442,"avg_volume_3m":941878,"volume_ratio":0.57,"breakout_score":50,"signal_type":"MONITOR"},{"id":"ICRA","symbol":"ICRA","company_name":"ICRA Limited","market_cap":50597511168,"market_cap_cr":5060,"current_price":5243.5,"price_change_pct":-1.48,"resistance_price":5329,"distance_pct":1.6,"current_volume":13735,"avg_volume_1m":9265,"avg_volume_2m":7278,"avg_volume_3m":7667,"volume_ratio":1.48,"breakout_score":50,"signal_type":"MONITOR"},{"id":"JKPAPER","symbol":"JKPAPER","company_name":"JK Paper Limited","market_cap":62972006400,"market_cap_cr":6297,"current_price":347.3,"price_change_pct":-0.74,"resistance_price":349.85,"distance_pct":0.73,"current_volume":307217,"avg_volume_1m":210381,"avg_volume_2m":361926,"avg_volume_3m":340524,"volume_ratio":1.46,"breakout_score":50,"signal_type":"MONITOR"},{"id":"LALPATHLAB","symbol":"LALPATHLAB","company_name":"Dr. Lal Path Labs Ltd.","market_cap":279153442816,"market_cap_cr":27915,"current_price":1671.8,"price_change_pct":2.2,"resistance_price":1698,"distance_pct":1.54,"current_volume":191277,"avg_volume_1m":646871,"avg_volume_2m":718517,"avg_volume_3m":598180,"volume_ratio":0.3,"breakout_score":50,"signal_type":"MONITOR"},{"id":"LICI","symbol":"LICI","company_name":"Life Insurance Corporation Of India","market_cap":2798178795520,"market_cap_cr":279818,"current_price":442.4,"price_change_pct":0.51,"resistance_price":448.25,"distance_pct":1.31,"current_volume":4708379,"avg_volume_1m":4999406,"avg_volume_2m":4601484,"avg_volume_3m":4440950,"volume_ratio":0.94,"breakout_score":50,"signal_type":"MONITOR"},{"id":"MARICO","symbol":"MARICO","company_name":"Marico Limited","market_cap":1052832890880,"market_cap_cr":105283,"current_price":812.45,"price_change_pct":-0.56,"resistance_price":813.5,"distance_pct":0.13,"current_volume":2006369,"avg_volume_1m":1915653,"avg_volume_2m":1858647,"avg_volume_3m":1928988,"volume_ratio":1.05,"breakout_score":50,"signal_type":"MONITOR"},{"id":"MCX","symbol":"MCX","company_name":"Multi Commodity Exchange of India Limited","market_cap":730557251584,"market_cap_cr":73056,"current_price":2870.4,"price_change_pct":2.38,"resistance_price":2903,"distance_pct":1.12,"current_volume":1810763,"avg_volume_1m":3579271,"avg_volume_2m":3201540,"avg_volume_3m":3432887,"volume_ratio":0.51,"breakout_score":50,"signal_type":"MONITOR"},{"id":"MGL","symbol":"MGL","company_name":"Mahanagar Gas Limited","market_cap":123027718144,"market_cap_cr":12303,"current_price":1245.5,"price_change_pct":3.02,"resistance_price":1233,"distance_pct":-1.01,"current_volume":408274,"avg_volume_1m":256081,"avg_volume_2m":229992,"avg_volume_3m":308892,"volume_ratio":1.59,"breakout_score":50,"signal_type":"MONITOR"},{"id":"NAUKRI","symbol":"NAUKRI","company_name":"Info Edge (India) Limited","market_cap":637729832960,"market_cap_cr":63773,"current_price":984.55,"price_change_pct":0.03,"resistance_price":996,"distance_pct":1.15,"current_volume":1305736,"avg_volume_1m":2305090,"avg_volume_2m":2142694,"avg_volume_3m":2173556,"volume_ratio":0.57,"breakout_score":50,"signal_type":"MONITOR"},{"id":"POWERGRID","symbol":"POWERGRID","company_name":"Power Grid Corporation of India Limited","market_cap":2694850019328,"market_cap_cr":269485,"current_price":289.75,"price_change_pct":-0.86,"resistance_price":293.05,"distance_pct":1.13,"current_volume":11677119,"avg_volume_1m":12586287,"avg_volume_2m":11292127,"avg_volume_3m":13018750,"volume_ratio":0.93,"breakout_score":50,"signal_type":"MONITOR"},{"id":"PPLPHARMA","symbol":"PPLPHARMA","company_name":"Piramal Pharma Limited","market_cap":210318032896,"market_cap_cr":21032,"current_price":158.51,"price_change_pct":-0.25,"resistance_price":160.54,"distance_pct":1.26,"current_volume":2708681,"avg_volume_1m":2578541,"avg_volume_2m":4840879,"avg_volume_3m":5055065,"volume_ratio":1.05,"breakout_score":50,"signal_type":"MONITOR"},{"id":"PTCIL","symbol":"PTCIL","company_name":"PTC Industries Limited","market_cap":268546539520,"market_cap_cr":26855,"current_price":17912,"price_change_pct":-2.3,"resistance_price":18250,"distance_pct":1.85,"current_volume":25305,"avg_volume_1m":39419,"avg_volume_2m":25432,"avg_volume_3m":23566,"volume_ratio":0.64,"breakout_score":50,"signal_type":"MONITOR"},{"id":"RAILTEL","symbol":"RAILTEL","company_name":"Railtel Corporation Of India Limited","market_cap":103823572992,"market_cap_cr":10382,"current_price":323.5,"price_change_pct":1.28,"resistance_price":330.5,"distance_pct":2.12,"current_volume":860521,"avg_volume_1m":760052,"avg_volume_2m":1117717,"avg_volume_3m":2765254,"volume_ratio":1.13,"breakout_score":50,"signal_type":"MONITOR"},{"id":"RELIANCE","symbol":"RELIANCE","company_name":"Reliance Industries Limited","market_cap":17950824202240,"market_cap_cr":1795082,"current_price":1326.5,"price_change_pct":1.3,"resistance_price":1371.1,"distance_pct":3.25,"current_volume":12927389,"avg_volume_1m":17064912,"avg_volume_2m":17868549,"avg_volume_3m":18857120,"volume_ratio":0.76,"breakout_score":50,"signal_type":"MONITOR"},{"id":"SANOFICONR","symbol":"SANOFICONR","company_name":"Sanofi Consumer Healthcare India Limited","market_cap":108855050240,"market_cap_cr":10886,"current_price":4719.8,"price_change_pct":-1.93,"resistance_price":4800,"distance_pct":1.67,"current_volume":5828,"avg_volume_1m":13190,"avg_volume_2m":11459,"avg_volume_3m":11856,"volume_ratio":0.44,"breakout_score":50,"signal_type":"MONITOR"},{"id":"SAREGAMA","symbol":"SAREGAMA","company_name":"Saregama India Limited","market_cap":91612667904,"market_cap_cr":9161,"current_price":477.25,"price_change_pct":2.44,"resistance_price":485,"distance_pct":1.6,"current_volume":764685,"avg_volume_1m":2204997,"avg_volume_2m":5094224,"avg_volume_3m":3541376,"volume_ratio":0.35,"breakout_score":50,"signal_type":"MONITOR"},{"id":"SYNGENE","symbol":"SYNGENE","company_name":"Syngene International Limited","market_cap":178180767744,"market_cap_cr":17818,"current_price":443.4,"price_change_pct":0.6,"resistance_price":448.65,"distance_pct":1.17,"current_volume":1124953,"avg_volume_1m":921853,"avg_volume_2m":2648911,"avg_volume_3m":2220680,"volume_ratio":1.22,"breakout_score":50,"signal_type":"MONITOR"},{"id":"TECHM","symbol":"TECHM","company_name":"Tech Mahindra Limited","market_cap":1271332208640,"market_cap_cr":127133,"current_price":1435.2,"price_change_pct":1.82,"resistance_price":1492.4,"distance_pct":3.83,"current_volume":2165276,"avg_volume_1m":2444603,"avg_volume_2m":2376344,"avg_volume_3m":2555251,"volume_ratio":0.89,"breakout_score":50,"signal_type":"MONITOR"},{"id":"THERMAX","symbol":"THERMAX","company_name":"Thermax Limited","market_cap":547911860224,"market_cap_cr":54791,"current_price":4863.9,"price_change_pct":3.43,"resistance_price":4880,"distance_pct":0.33,"current_volume":223699,"avg_volume_1m":300124,"avg_volume_2m":344637,"avg_volume_3m":314269,"volume_ratio":0.75,"breakout_score":50,"signal_type":"MONITOR"},{"id":"THOMASCOOK","symbol":"THOMASCOOK","company_name":"Thomas Cook  (India)  Limited","market_cap":54387511296,"market_cap_cr":5439,"current_price":115.1,"price_change_pct":3.14,"resistance_price":115.99,"distance_pct":0.77,"current_volume":2475716,"avg_volume_1m":7617334,"avg_volume_2m":4476762,"avg_volume_3m":3456141,"volume_ratio":0.33,"breakout_score":50,"signal_type":"MONITOR"},{"id":"TORNTPHARM","symbol":"TORNTPHARM","company_name":"Torrent Pharmaceuticals Limited","market_cap":1508451287040,"market_cap_cr":150845,"current_price":4457,"price_change_pct":0.61,"resistance_price":4470,"distance_pct":0.29,"current_volume":704689,"avg_volume_1m":601100,"avg_volume_2m":434598,"avg_volume_3m":429921,"volume_ratio":1.17,"breakout_score":50,"signal_type":"MONITOR"},{"id":"TRANSRAILL","symbol":"TRANSRAILL","company_name":"Transrail Lighting Limited","market_cap":69537914880,"market_cap_cr":6954,"current_price":517.95,"price_change_pct":2.02,"resistance_price":528.5,"distance_pct":2,"current_volume":672309,"avg_volume_1m":683612,"avg_volume_2m":684176,"avg_volume_3m":748656,"volume_ratio":0.98,"breakout_score":50,"signal_type":"MONITOR"},{"id":"TRITURBINE","symbol":"TRITURBINE","company_name":"Triveni Turbine Limited","market_cap":234383966208,"market_cap_cr":23438,"current_price":737.3,"price_change_pct":9.67,"resistance_price":787.6,"distance_pct":6.39,"current_volume":5383692,"avg_volume_1m":1334345,"avg_volume_2m":2529034,"avg_volume_3m":3210559,"volume_ratio":4.03,"breakout_score":50,"signal_type":"MONITOR"},{"id":"ZEEL","symbol":"ZEEL","company_name":"Zee Entertainment Enterprises Limited","market_cap":111180120064,"market_cap_cr":11118,"current_price":115.75,"price_change_pct":2.11,"resistance_price":117.2,"distance_pct":1.24,"current_volume":38108369,"avg_volume_1m":65410933,"avg_volume_2m":39744573,"avg_volume_3m":34069759,"volume_ratio":0.58,"breakout_score":50,"signal_type":"MONITOR"}]}